Workbook

Sheet Cover & Assumptions
B2: GUSTO PEO — COST COMPARISON MODEL
B3: Current state vs. Gusto PEO — prepared for the client
B5: Year-1 Savings | C5: Current Annual Cost | D5: Gusto PEO Annual Cost | E5: Savings %
B6: =C24-C25 -> 75150 | C6: =C24 -> 1189200 | D6: =C25 -> 1114050 | E6: =IF(C24=0,0,(C24-C25)/C24) -> 0.063193744
B9: ASSUMPTIONS
B10: Client / Account name | C10: Sample Client Co.
B11: Current provider | C11: Current Carrier / PEO
B12: Employees (WSEs) | C12: 25
B13: Annual benefit trend | C13: 0.07
B14: Gusto PEO admin fee (PEPM) | C14: 95
B16: Blue cells are inputs. Edit those only; everything else calculates.
B23: ANNUAL TOTALS (ALL EMPLOYEES)
B24: Current annual cost | C24: ='Major Medical'!E20+Dental!E14+Vision!E14+'Workers Comp'!E14 -> 1189200
B25: Gusto PEO annual cost | C25: ='Major Medical'!F20+Dental!F14+Vision!F14+'Workers Comp'!F14+(C12*C14*12) -> 1114050

Sheet Major Medical
B2: MAJOR MEDICAL — CURRENT VS GUSTO PEO
B4: Line item | C4: Current PEPM | D4: Gusto PEPM | E4: Current Annual | F4: Gusto Annual
B5: Employee Only | C5: 450 | D5: 410 | E5: =C5*'Cover & Assumptions'!$C$12*12 -> 135000 | F5: =D5*'Cover & Assumptions'!$C$12*12 -> 123000
B6: Employee + Spouse | C6: 720 | D6: 660 | E6: =C6*'Cover & Assumptions'!$C$12*12 -> 216000 | F6: =D6*'Cover & Assumptions'!$C$12*12 -> 198000
B7: Employee + Child(ren) | C7: 680 | D7: 620 | E7: =C7*'Cover & Assumptions'!$C$12*12 -> 204000 | F7: =D7*'Cover & Assumptions'!$C$12*12 -> 186000
B8: Family | C8: 980 | D8: 900 | E8: =C8*'Cover & Assumptions'!$C$12*12 -> 294000 | F8: =D8*'Cover & Assumptions'!$C$12*12 -> 270000
B9: Buy-up / Premium plan | C9: 560 | D9: 515 | E9: =C9*'Cover & Assumptions'!$C$12*12 -> 168000 | F9: =D9*'Cover & Assumptions'!$C$12*12 -> 154500
B10: (blended avg used below) | C10: 0 | D10: 0 | E10: =C10*'Cover & Assumptions'!$C$12*12 -> 0 | F10: =D10*'Cover & Assumptions'!$C$12*12 -> 0
B19: Blended PEPM (all tiers) | C19: 380 | D19: 348 | E19: =C19*'Cover & Assumptions'!$C$12*12 -> 114000 | F19: =D19*'Cover & Assumptions'!$C$12*12 -> 104400
B20: TOTAL | C20: =SUM(C5:C19) -> 380 | D20: =SUM(D5:D19) -> 348 | E20: =SUM(E5:E19) -> 1131000 | F20: =SUM(F5:F19) -> 1035900

Sheet Dental
B2: DENTAL — CURRENT VS GUSTO PEO
B4: Line item | C4: Current PEPM | D4: Gusto PEPM | E4: Current Annual | F4: Gusto Annual
B5: Employee Only | C5: 32 | D5: 28 | E5: =C5*'Cover & Assumptions'!$C$12*12 -> 9600 | F5: =D5*'Cover & Assumptions'!$C$12*12 -> 8400
B6: Family | C6: 78 | D6: 70 | E6: =C6*'Cover & Assumptions'!$C$12*12 -> 23400 | F6: =D6*'Cover & Assumptions'!$C$12*12 -> 21000
B14: TOTAL | C14: =SUM(C5:C13) -> 0 | D14: =SUM(D5:D13) -> 0 | E14: =SUM(E5:E13) -> 33000 | F14: =SUM(F5:F13) -> 29400

Sheet Vision
B2: VISION — CURRENT VS GUSTO PEO
B4: Line item | C4: Current PEPM | D4: Gusto PEPM | E4: Current Annual | F4: Gusto Annual
B5: Employee Only | C5: 8 | D5: 6.5 | E5: =C5*'Cover & Assumptions'!$C$12*12 -> 2400 | F5: =D5*'Cover & Assumptions'!$C$12*12 -> 1950
B6: Family | C6: 18 | D6: 15 | E6: =C6*'Cover & Assumptions'!$C$12*12 -> 5400 | F6: =D6*'Cover & Assumptions'!$C$12*12 -> 4500
B14: TOTAL | C14: =SUM(C5:C13) -> 0 | D14: =SUM(D5:D13) -> 0 | E14: =SUM(E5:E13) -> 7800 | F14: =SUM(F5:F13) -> 6450

Sheet Workers Comp
B2: WORKERS COMP — CURRENT VS GUSTO PEO
B4: Line item | C4: Current PEPM | D4: Gusto PEPM | E4: Current Annual | F4: Gusto Annual
B5: Comp premium (blended PEPM) | C5: 58 | D5: 46 | E5: =C5*'Cover & Assumptions'!$C$12*12 -> 17400 | F5: =D5*'Cover & Assumptions'!$C$12*12 -> 13800
B14: TOTAL | C14: =SUM(C5:C13) -> 0 | D14: =SUM(D5:D13) -> 0 | E14: =SUM(E5:E13) -> 17400 | F14: =SUM(F5:F13) -> 13800

Sheet ROI Summary
B2: ROI SUMMARY
B4: Category | C4: Current | D4: Gusto PEO | E4: Annual Savings
B5: Major Medical | C5: ='Major Medical'!E20 -> 1131000 | D5: ='Major Medical'!F20 -> 1035900 | E5: =C5-D5 -> 95100
B6: Dental | C6: =Dental!E14 -> 33000 | D6: =Dental!F14 -> 29400 | E6: =C6-D6 -> 3600
B7: Vision | C7: =Vision!E14 -> 7800 | D7: =Vision!F14 -> 6450 | E7: =C7-D7 -> 1350
B8: Workers' Comp | C8: ='Workers Comp'!E14 -> 17400 | D8: ='Workers Comp'!F14 -> 13800 | E8: =C8-D8 -> 3600
B9: PEO Admin Fee | C9: =0 -> 0 | D9: ='Cover & Assumptions'!$C$12*'Cover & Assumptions'!$C$14*12 -> 28500 | E9: =C9-D9 -> -28500
B10: TOTAL | C10: =SUM(C5:C9) -> 1189200 | D10: =SUM(D5:D9) -> 1114050 | E10: =SUM(E5:E9) -> 75150
B12: Year-1 savings % | C12: =IF(C10=0,0,E10/C10) -> 0.063193744

Sheet 4-Year Projection
B2: FOUR-YEAR PROJECTION
B4: Year | C4: Current | D4: Gusto PEO | E4: Annual Savings | F4: Cumulative Savings
B5: Year 1 | C5: ='ROI Summary'!C10*(1+'Cover & Assumptions'!$C$13)^0 -> 1189200 | D5: ='ROI Summary'!D10*(1+'Cover & Assumptions'!$C$13)^0 -> 1114050 | E5: =C5-D5 -> 75150 | F5: =E5 -> 75150
B6: Year 2 | C6: ='ROI Summary'!C10*(1+'Cover & Assumptions'!$C$13)^1 -> 1272444 | D6: ='ROI Summary'!D10*(1+'Cover & Assumptions'!$C$13)^1 -> 1192033.5 | E6: =C6-D6 -> 80410.5 | F6: =F5+E6 -> 155560.5
B7: Year 3 | C7: ='ROI Summary'!C10*(1+'Cover & Assumptions'!$C$13)^2 -> 1361515.1 | D7: ='ROI Summary'!D10*(1+'Cover & Assumptions'!$C$13)^2 -> 1275475.8 | E7: =C7-D7 -> 86039.235 | F7: =F6+E7 -> 241599.73
B8: Year 4 | C8: ='ROI Summary'!C10*(1+'Cover & Assumptions'!$C$13)^3 -> 1456821.1 | D8: ='ROI Summary'!D10*(1+'Cover & Assumptions'!$C$13)^3 -> 1364759.2 | E8: =C8-D8 -> 92061.981 | F8: =F7+E8 -> 333661.72

Sheet Included Services
B2: WHAT THE GUSTO PEO INCLUDES
B4: Payroll processing & tax filing | C4: Included
B5: Master medical / dental / vision plans | C5: Included
B6: Workers' comp (pay-as-you-go) | C6: Included
B7: HR platform & self-serve | C7: Included
B8: Compliance & ACA support | C8: Included
B9: 401(k) administration | C9: Included
B10: Onboarding & benefits enrollment | C10: Included
B11: Dedicated support | C11: Included
B13: Always extra (pass-through, billed at cost): wages, employer taxes, insurance premiums, 401(k) employer contributions.
